{".class": "MypyFile", "_fullname": "stonks", "is_partial_stub_package": false, "is_stub": false, "names": {".class": "SymbolTable", "APIKey": {".class": "SymbolTableNode", "kind": "Gdef", "node": {".class": "Var", "flags": [], "fullname": "stonks.APIKey", "name": "APIKey", "type": "builtins.str"}}, "Request": {".class": "SymbolTableNode", "cross_ref": "requests.Request", "kind": "Gdef"}, "Session": {".class": "SymbolTableNode", "cross_ref": "requests.Session", "kind": "Gdef"}, "Timeout": {".class": "SymbolTableNode", "cross_ref": "requests.exceptions.Timeout", "kind": "Gdef"}, "TooManyRedirects": {".class": "SymbolTableNode", "cross_ref": "requests.exceptions.TooManyRedirects", "kind": "Gdef"}, "__doc__": {".class": "SymbolTableNode", "kind": "Gdef", "node": {".class": "Var", "flags": ["is_ready"], "fullname": "stonks.__doc__", "name": "__doc__", "type": "builtins.str"}}, "__file__": {".class": "SymbolTableNode", "kind": "Gdef", "node": {".class": "Var", "flags": ["is_ready"], "fullname": "stonks.__file__", "name": "__file__", "type": "builtins.str"}}, "__name__": {".class": "SymbolTableNode", "kind": "Gdef", "node": {".class": "Var", "flags": ["is_ready"], "fullname": "stonks.__name__", "name": "__name__", "type": "builtins.str"}}, "__package__": {".class": "SymbolTableNode", "kind": "Gdef", "node": {".class": "Var", "flags": ["is_ready"], "fullname": "stonks.__package__", "name": "__package__", "type": "builtins.str"}}, "aliases": {".class": "SymbolTableNode", "kind": "Gdef", "node": {".class": "Var", "flags": [], "fullname": "stonks.aliases", "name": "aliases", "type": {".class": "Instance", "args": ["builtins.str", {".class": "Instance", "args": ["builtins.str"], "type_ref": "builtins.list"}], "type_ref": "builtins.dict"}}}, "base_currency": {".class": "SymbolTableNode", "kind": "Gdef", "node": {".class": "Var", "flags": [], "fullname": "stonks.base_currency", "name": "base_currency", "type": "builtins.str"}}, "change": {".class": "SymbolTableNode", "kind": "Gdef", "node": {".class": "Var", "flags": [], "fullname": "stonks.change", "name": "change", "type": {".class": "AnyType", "missing_import_name": null, "source_any": {".class": "AnyType", "missing_import_name": null, "source_any": null, "type_of_any": 2}, "type_of_any": 7}}}, "config": {".class": "SymbolTableNode", "kind": "Gdef", "node": {".class": "Var", "flags": [], "fullname": "stonks.config", "name": "config", "type": "configparser.SectionProxy"}}, "configparser": {".class": "SymbolTableNode", "cross_ref": "configparser", "kind": "Gdef"}, "configuration": {".class": "SymbolTableNode", "kind": "Gdef", "node": {".class": "Var", "flags": [], "fullname": "stonks.configuration", "name": "configuration", "type": "configparser.ConfigParser"}}, "currencies": {".class": "SymbolTableNode", "kind": "Gdef", "node": {".class": "Var", "flags": [], "fullname": "stonks.currencies", "name": "currencies", "type": "builtins.str"}}, "currency": {".class": "SymbolTableNode", "kind": "Gdef", "node": {".class": "Var", "flags": [], "fullname": "stonks.currency", "name": "currency", "type": "builtins.str"}}, "data": {".class": "SymbolTableNode", "kind": "Gdef", "node": {".class": "Var", "flags": [], "fullname": "stonks.data", "name": "data", "type": {".class": "AnyType", "missing_import_name": null, "source_any": {".class": "AnyType", "missing_import_name": null, "source_any": null, "type_of_any": 2}, "type_of_any": 7}}}, "display": {".class": "SymbolTableNode", "kind": "Gdef", "node": {".class": "Var", "flags": [], "fullname": "stonks.display", "name": "display", "type": "builtins.str"}}, "e": {".class": "SymbolTableNode", "kind": "Gdef", "node": {".class": "Var", "flags": [], "fullname": "stonks.e", "name": "e", "type": {".class": "DeletedType", "source": "e"}}}, "f": {".class": "SymbolTableNode", "kind": "Gdef", "node": {".class": "Var", "flags": [], "fullname": "stonks.f", "name": "f", "type": "typing.TextIO"}}, "headers": {".class": "SymbolTableNode", "kind": "Gdef", "node": {".class": "Var", "flags": [], "fullname": "stonks.headers", "name": "headers", "type": {".class": "Instance", "args": ["builtins.str", "builtins.str"], "type_ref": "builtins.dict"}}}, "json": {".class": "SymbolTableNode", "cross_ref": "json", "kind": "Gdef"}, "local_price": {".class": "SymbolTableNode", "kind": "Gdef", "node": {".class": "Var", "flags": [], "fullname": "stonks.local_price", "name": "local_price", "type": {".class": "AnyType", "missing_import_name": null, "source_any": {".class": "AnyType", "missing_import_name": null, "source_any": null, "type_of_any": 2}, "type_of_any": 7}}}, "opt": {".class": "SymbolTableNode", "kind": "Gdef", "node": {".class": "Var", "flags": [], "fullname": "stonks.opt", "name": "opt", "type": {".class": "Instance", "args": ["builtins.str"], "type_ref": "builtins.list"}}}, "options": {".class": "SymbolTableNode", "kind": "Gdef", "node": {".class": "Var", "flags": [], "fullname": "stonks.options", "name": "options", "type": {".class": "Instance", "args": ["builtins.str"], "type_ref": "builtins.list"}}}, "params": {".class": "SymbolTableNode", "kind": "Gdef", "node": {".class": "Var", "flags": [], "fullname": "stonks.params", "name": "params", "type": {".class": "Instance", "args": ["builtins.str", "builtins.str"], "type_ref": "builtins.dict"}}}, "percentchg": {".class": "SymbolTableNode", "kind": "Gdef", "node": {".class": "Var", "flags": [], "fullname": "stonks.percentchg", "name": "percentchg", "type": {".class": "Instance", "args": [{".class": "Instance", "args": ["builtins.str"], "type_ref": "builtins.list"}], "type_ref": "builtins.list"}}}, "percents": {".class": "SymbolTableNode", "kind": "Gdef", "node": {".class": "Var", "flags": [], "fullname": "stonks.percents", "name": "percents", "type": "builtins.bool"}}, "response": {".class": "SymbolTableNode", "kind": "Gdef", "node": {".class": "Var", "flags": [], "fullname": "stonks.response", "name": "response", "type": "requests.models.Response"}}, "session": {".class": "SymbolTableNode", "kind": "Gdef", "node": {".class": "Var", "flags": [], "fullname": "stonks.session", "name": "session", "type": "requests.sessions.Session"}}, "sys": {".class": "SymbolTableNode", "cross_ref": "sys", "kind": "Gdef"}, "url": {".class": "SymbolTableNode", "kind": "Gdef", "node": {".class": "Var", "flags": ["is_ready"], "fullname": "stonks.url", "name": "url", "type": "builtins.str"}}, "val": {".class": "SymbolTableNode", "kind": "Gdef", "node": {".class": "Var", "flags": [], "fullname": "stonks.val", "name": "val", "type": "builtins.str"}}}, "path": "/home/normie/.config/polybar/stonks/stonks.py"}